progiter/__init__.py
progiter/manager.py
progiter/progiter.py
progiter-2.0.0.dist-info/LICENSE
progiter-2.0.0.dist-info/METADATA
progiter-2.0.0.dist-info/WHEEL
progiter-2.0.0.dist-info/top_level.txt
progiter-2.0.0.dist-info/RECORD
