Metadata-Version: 2.1
Name: progiter
Version: 2.0.0
Summary: A single-threaded alternative to tqdm.
Home-page: UNKNOWN
Author: Jon Crall
Author-email: erotemic@gmail.com
License: Apache 2
Platform: UNKNOWN
Classifier: Development Status :: 5 - Production/Stable
Classifier: Intended Audience :: Developers
Classifier: Topic :: Software Development :: Libraries :: Python Modules
Classifier: Topic :: Utilities
Classifier: License :: OSI Approved :: Apache Software License
Classifier: Programming Language :: Python :: 3.6
Classifier: Programming Language :: Python :: 3.7
Classifier: Programming Language :: Python :: 3.8
Classifier: Programming Language :: Python :: 3.9
Classifier: Programming Language :: Python :: 3.10
Classifier: Programming Language :: Python :: 3.11
Requires-Python: >=3.6
Provides-Extra: all
Provides-Extra: all-strict
Provides-Extra: optional
Provides-Extra: optional-strict
Provides-Extra: runtime-strict
Provides-Extra: tests
Provides-Extra: tests-strict
License-File: LICENSE
